{"type":"Scene","props":{"width":1280,"height":720},"compId":2,"child":[{"type":"Panel","props":{"y":0,"x":0,"width":1280,"vScrollBarSkin":"public/vscroll.png","name":"map","height":720,"hScrollBarSkin":"public/hscroll.png","cacheAs":"bitmap"},"compId":43,"child":[{"type":"Sprite","props":{"y":-499,"x":-715,"name":"map","cacheAs":"bitmap"},"compId":45,"child":[{"type":"Sprite","props":{"y":-157,"x":478,"width":1900,"texture":"game/map.png","name":"bg","height":1373},"compId":42},{"type":"Sprite","props":{"y":277,"x":1405,"texture":"map/邯郸.png","name":"map_handan"},"compId":268},{"type":"Sprite","props":{"y":383,"x":1265,"texture":"map/韩.png","name":"map_han"},"compId":270},{"type":"Sprite","props":{"y":451,"x":1400,"texture":"map/魏.png","name":"map_wei"},"compId":271},{"type":"Sprite","props":{"y":371,"x":1708,"texture":"map/齐郡.png","name":"map_qijun"},"compId":272},{"type":"Sprite","props":{"y":521,"x":964,"texture":"map/内史.png","name":"map_neishi"},"compId":44},{"type":"Sprite","props":{"y":-40,"x":1111,"texture":"map/上郡.png","name":"map_shangjun"},"compId":251},{"type":"Sprite","props":{"y":266,"x":1599,"texture":"map/东郡.png","name":"map_dongjun"},"compId":252},{"type":"Sprite","props":{"y":189,"x":1485,"texture":"map/中山.png","name":"map_zhongshan"},"compId":253},{"type":"Sprite","props":{"y":-29,"x":1318,"texture":"map/代郡.png","name":"map_daijun"},"compId":254},{"type":"Sprite","props":{"y":921,"x":923,"texture":"map/南郡.png","name":"map_nanjun"},"compId":256},{"type":"Sprite","props":{"y":760,"x":1248,"texture":"map/南阳.png","name":"map_nanyang"},"compId":257},{"type":"Sprite","props":{"y":180,"x":1223,"texture":"map/太原.png","name":"map_taiyuan"},"compId":258},{"type":"Sprite","props":{"y":626,"x":1572,"texture":"map/宋.png","name":"map_song"},"compId":259},{"type":"Sprite","props":{"y":731,"x":554,"texture":"map/巴蜀.png","name":"map_bashu"},"compId":260},{"type":"Sprite","props":{"y":687,"x":894,"texture":"map/汉中.png","name":"map_hanzhong"},"compId":261},{"type":"Sprite","props":{"y":398,"x":1167,"texture":"map/河东.png","name":"map_hedong"},"compId":262},{"type":"Sprite","props":{"y":729,"x":1457,"texture":"map/泗水.png","name":"map_sishui"},"compId":263},{"type":"Sprite","props":{"y":503,"x":835,"texture":"map/陇西.png","name":"map_longxi"},"compId":269},{"type":"Sprite","props":{"y":472,"x":1643,"texture":"map/琅琊.png","name":"map_langya"},"compId":266},{"type":"Sprite","props":{"y":-29,"x":1538,"texture":"map/燕.png","name":"map_yan"},"compId":265},{"type":"Sprite","props":{"y":659,"x":1682,"texture":"map/淮夷.png","name":"map_huaiyi"},"compId":264},{"type":"Sprite","props":{"y":904,"x":1427,"texture":"map/豫章.png","name":"map_yuzhang"},"compId":267},{"type":"Sprite","props":{"y":619,"x":1611,"scaleY":0.2,"scaleX":0.2,"name":"song"},"compId":275,"child":[{"type":"Sprite","props":{"x":12,"texture":"image/国-宋.png","name":"hero"},"compId":47},{"type":"Sprite","props":{"y":147,"x":13,"texture":"image/国-宋.png","name":"soliders"},"compId":49},{"type":"Clip","props":{"y":324,"skin":"public/clip_num_blue.png","scaleY":5,"scaleX":5,"name":"moved","clipX":10},"compId":273},{"type":"Clip","props":{"y":150,"x":15,"skin":"public/clip_num_red.png","scaleY":5,"scaleX":5,"name":"moving","clipX":10},"compId":274}]},{"type":"Sprite","props":{"y":521,"x":1787.5,"scaleY":0.2,"scaleX":0.2,"name":"langya"},"compId":276,"child":[{"type":"Sprite","props":{"x":12,"texture":"image/国-宋.png","name":"hero"},"compId":277},{"type":"Sprite","props":{"y":147,"x":13,"texture":"image/国-宋.png","name":"soliders"},"compId":278},{"type":"Clip","props":{"y":324,"skin":"public/clip_num_blue.png","scaleY":5,"scaleX":5,"name":"moved","clipX":10},"compId":279},{"type":"Clip","props":{"y":150,"x":15,"skin":"public/clip_num_red.png","scaleY":5,"scaleX":5,"name":"moving","clipX":10},"compId":280}]},{"type":"Sprite","props":{"y":960,"x":743,"scaleY":0.2,"scaleX":0.2,"name":"bashu"},"compId":281,"child":[{"type":"Sprite","props":{"x":12,"texture":"image/国-宋.png","name":"hero"},"compId":282},{"type":"Sprite","props":{"y":147,"x":13,"texture":"image/国-宋.png","name":"soliders"},"compId":283},{"type":"Clip","props":{"y":324,"skin":"public/clip_num_blue.png","scaleY":5,"scaleX":5,"name":"moved","clipX":10},"compId":284},{"type":"Clip","props":{"y":150,"x":15,"skin":"public/clip_num_red.png","scaleY":5,"scaleX":5,"name":"moving","clipX":10},"compId":285}]},{"type":"Sprite","props":{"y":232,"x":1538,"scaleY":0.2,"scaleX":0.2,"name":"zhongshan"},"compId":286,"child":[{"type":"Sprite","props":{"x":12,"texture":"image/国-宋.png","name":"hero"},"compId":287},{"type":"Sprite","props":{"y":147,"x":13,"texture":"image/国-宋.png","name":"soliders"},"compId":288},{"type":"Clip","props":{"y":324,"skin":"public/clip_num_blue.png","scaleY":5,"scaleX":5,"name":"moved","clipX":10},"compId":289},{"type":"Clip","props":{"y":150,"x":15,"skin":"public/clip_num_red.png","scaleY":5,"scaleX":5,"name":"moving","clipX":10},"compId":290}]},{"type":"Sprite","props":{"y":380,"x":1805,"scaleY":0.2,"scaleX":0.2,"name":"qijun"},"compId":291,"child":[{"type":"Sprite","props":{"x":12,"texture":"image/国-宋.png","name":"hero"},"compId":292},{"type":"Sprite","props":{"y":147,"x":13,"texture":"image/国-宋.png","name":"soliders"},"compId":293},{"type":"Clip","props":{"y":324,"skin":"public/clip_num_blue.png","scaleY":5,"scaleX":5,"name":"moved","clipX":10},"compId":294},{"type":"Clip","props":{"y":150,"x":15,"skin":"public/clip_num_red.png","scaleY":5,"scaleX":5,"name":"moving","clipX":10},"compId":295}]},{"type":"Sprite","props":{"y":411,"x":1635.5,"scaleY":0.2,"scaleX":0.2,"name":"dongjun"},"compId":296,"child":[{"type":"Sprite","props":{"x":12,"texture":"image/国-宋.png","name":"hero"},"compId":297},{"type":"Sprite","props":{"y":147,"x":13,"texture":"image/国-宋.png","name":"soliders"},"compId":298},{"type":"Clip","props":{"y":324,"skin":"public/clip_num_blue.png","scaleY":5,"scaleX":5,"name":"moved","clipX":10},"compId":299},{"type":"Clip","props":{"y":150,"x":15,"skin":"public/clip_num_red.png","scaleY":5,"scaleX":5,"name":"moving","clipX":10},"compId":300}]},{"type":"Sprite","props":{"y":594.5,"x":1338,"scaleY":0.2,"scaleX":0.2,"name":"han"},"compId":301,"child":[{"type":"Sprite","props":{"x":12,"texture":"image/国-宋.png","name":"hero"},"compId":302},{"type":"Sprite","props":{"y":147,"x":13,"texture":"image/国-宋.png","name":"soliders"},"compId":303},{"type":"Clip","props":{"y":324,"skin":"public/clip_num_blue.png","scaleY":5,"scaleX":5,"name":"moved","clipX":10},"compId":304},{"type":"Clip","props":{"y":150,"x":15,"skin":"public/clip_num_red.png","scaleY":5,"scaleX":5,"name":"moving","clipX":10},"compId":305}]},{"type":"Sprite","props":{"y":582,"x":1509,"scaleY":0.2,"scaleX":0.2,"name":"wei"},"compId":306,"child":[{"type":"Sprite","props":{"x":12,"texture":"image/国-宋.png","name":"hero"},"compId":307},{"type":"Sprite","props":{"y":147,"x":13,"texture":"image/国-宋.png","name":"soliders"},"compId":308},{"type":"Clip","props":{"y":324,"skin":"public/clip_num_blue.png","scaleY":5,"scaleX":5,"name":"moved","clipX":10},"compId":309},{"type":"Clip","props":{"y":150,"x":15,"skin":"public/clip_num_red.png","scaleY":5,"scaleX":5,"name":"moving","clipX":10},"compId":310}]},{"type":"Sprite","props":{"y":601,"x":865.75,"scaleY":0.2,"scaleX":0.2,"name":"longxi"},"compId":311,"child":[{"type":"Sprite","props":{"x":12,"texture":"image/国-宋.png","name":"hero"},"compId":312},{"type":"Sprite","props":{"y":147,"x":13,"texture":"image/国-宋.png","name":"soliders"},"compId":313},{"type":"Clip","props":{"y":324,"skin":"public/clip_num_blue.png","scaleY":5,"scaleX":5,"name":"moved","clipX":10},"compId":314},{"type":"Clip","props":{"y":150,"x":15,"skin":"public/clip_num_red.png","scaleY":5,"scaleX":5,"name":"moving","clipX":10},"compId":315}]},{"type":"Sprite","props":{"y":762.5,"x":945,"scaleY":0.2,"scaleX":0.2,"name":"hanzhong"},"compId":316,"child":[{"type":"Sprite","props":{"x":12,"texture":"image/国-宋.png","name":"hero"},"compId":317},{"type":"Sprite","props":{"y":147,"x":13,"texture":"image/国-宋.png","name":"soliders"},"compId":318},{"type":"Clip","props":{"y":324,"skin":"public/clip_num_blue.png","scaleY":5,"scaleX":5,"name":"moved","clipX":10},"compId":319},{"type":"Clip","props":{"y":150,"x":15,"skin":"public/clip_num_red.png","scaleY":5,"scaleX":5,"name":"moving","clipX":10},"compId":320}]},{"type":"Sprite","props":{"y":967.5,"x":1531.5,"scaleY":0.2,"scaleX":0.2,"name":"yuzhang"},"compId":321,"child":[{"type":"Sprite","props":{"x":12,"texture":"image/国-宋.png","name":"hero"},"compId":322},{"type":"Sprite","props":{"y":147,"x":13,"texture":"image/国-宋.png","name":"soliders"},"compId":323},{"type":"Clip","props":{"y":324,"skin":"public/clip_num_blue.png","scaleY":5,"scaleX":5,"name":"moved","clipX":10},"compId":324},{"type":"Clip","props":{"y":150,"x":15,"skin":"public/clip_num_red.png","scaleY":5,"scaleX":5,"name":"moving","clipX":10},"compId":325}]},{"type":"Sprite","props":{"y":643.5,"x":1075,"scaleY":0.2,"scaleX":0.2,"name":"neishi"},"compId":326,"child":[{"type":"Sprite","props":{"x":12,"texture":"image/国-宋.png","name":"hero"},"compId":327},{"type":"Sprite","props":{"y":147,"x":13,"texture":"image/国-宋.png","name":"soliders"},"compId":328},{"type":"Clip","props":{"y":324,"skin":"public/clip_num_blue.png","scaleY":5,"scaleX":5,"name":"moved","clipX":10},"compId":329},{"type":"Clip","props":{"y":150,"x":15,"skin":"public/clip_num_red.png","scaleY":5,"scaleX":5,"name":"moving","clipX":10},"compId":330}]},{"type":"Sprite","props":{"y":774,"x":1543,"scaleY":0.2,"scaleX":0.2,"name":"sishui"},"compId":331,"child":[{"type":"Sprite","props":{"x":12,"texture":"image/国-宋.png","name":"hero"},"compId":332},{"type":"Sprite","props":{"y":147,"x":13,"texture":"image/国-宋.png","name":"soliders"},"compId":333},{"type":"Clip","props":{"y":324,"skin":"public/clip_num_blue.png","scaleY":5,"scaleX":5,"name":"moved","clipX":10},"compId":334},{"type":"Clip","props":{"y":150,"x":15,"skin":"public/clip_num_red.png","scaleY":5,"scaleX":5,"name":"moving","clipX":10},"compId":335}]},{"type":"Sprite","props":{"y":429.5,"x":1161.5,"scaleY":0.2,"scaleX":0.2,"name":"shangjun"},"compId":336,"child":[{"type":"Sprite","props":{"x":12,"texture":"image/国-宋.png","name":"hero"},"compId":337},{"type":"Sprite","props":{"y":147,"x":13,"texture":"image/国-宋.png","name":"soliders"},"compId":338},{"type":"Clip","props":{"y":324,"skin":"public/clip_num_blue.png","scaleY":5,"scaleX":5,"name":"moved","clipX":10},"compId":339},{"type":"Clip","props":{"y":150,"x":15,"skin":"public/clip_num_red.png","scaleY":5,"scaleX":5,"name":"moving","clipX":10},"compId":340}]},{"type":"Sprite","props":{"y":894.5,"x":1724.5,"scaleY":0.2,"scaleX":0.2,"name":"huaiyi"},"compId":341,"child":[{"type":"Sprite","props":{"x":12,"texture":"image/国-宋.png","name":"hero"},"compId":342},{"type":"Sprite","props":{"y":147,"x":13,"texture":"image/国-宋.png","name":"soliders"},"compId":343},{"type":"Clip","props":{"y":324,"skin":"public/clip_num_blue.png","scaleY":5,"scaleX":5,"name":"moved","clipX":10},"compId":344},{"type":"Clip","props":{"y":150,"x":15,"skin":"public/clip_num_red.png","scaleY":5,"scaleX":5,"name":"moving","clipX":10},"compId":345}]},{"type":"Sprite","props":{"y":380,"x":1484,"scaleY":0.2,"scaleX":0.2,"name":"handan"},"compId":346,"child":[{"type":"Sprite","props":{"x":12,"texture":"image/国-宋.png","name":"hero"},"compId":347},{"type":"Sprite","props":{"y":147,"x":13,"texture":"image/国-宋.png","name":"soliders"},"compId":348},{"type":"Clip","props":{"y":324,"skin":"public/clip_num_blue.png","scaleY":5,"scaleX":5,"name":"moved","clipX":10},"compId":349},{"type":"Clip","props":{"y":150,"x":15,"skin":"public/clip_num_red.png","scaleY":5,"scaleX":5,"name":"moving","clipX":10},"compId":350}]},{"type":"Sprite","props":{"y":266,"x":1314,"scaleY":0.2,"scaleX":0.2,"name":"taiyuan"},"compId":351,"child":[{"type":"Sprite","props":{"x":12,"texture":"image/国-宋.png","name":"hero"},"compId":352},{"type":"Sprite","props":{"y":147,"x":13,"texture":"image/国-宋.png","name":"soliders"},"compId":353},{"type":"Clip","props":{"y":324,"skin":"public/clip_num_blue.png","scaleY":5,"scaleX":5,"name":"moved","clipX":10},"compId":354},{"type":"Clip","props":{"y":150,"x":15,"skin":"public/clip_num_red.png","scaleY":5,"scaleX":5,"name":"moving","clipX":10},"compId":355}]},{"type":"Sprite","props":{"y":88,"x":1473,"scaleY":0.2,"scaleX":0.2,"name":"daijun"},"compId":371,"child":[{"type":"Sprite","props":{"x":12,"texture":"image/国-宋.png","name":"hero"},"compId":372},{"type":"Sprite","props":{"y":147,"x":13,"texture":"image/国-宋.png","name":"soliders"},"compId":373},{"type":"Clip","props":{"y":324,"skin":"public/clip_num_blue.png","scaleY":5,"scaleX":5,"name":"moved","clipX":10},"compId":374},{"type":"Clip","props":{"y":150,"x":15,"skin":"public/clip_num_red.png","scaleY":5,"scaleX":5,"name":"moving","clipX":10},"compId":375}]},{"type":"Sprite","props":{"y":101,"x":1638.5,"scaleY":0.2,"scaleX":0.2,"name":"yan"},"compId":376,"child":[{"type":"Sprite","props":{"x":12,"texture":"image/国-宋.png","name":"hero"},"compId":377},{"type":"Sprite","props":{"y":147,"x":13,"texture":"image/国-宋.png","name":"soliders"},"compId":378},{"type":"Clip","props":{"y":324,"skin":"public/clip_num_blue.png","scaleY":5,"scaleX":5,"name":"moved","clipX":10},"compId":379},{"type":"Clip","props":{"y":150,"x":15,"skin":"public/clip_num_red.png","scaleY":5,"scaleX":5,"name":"moving","clipX":10},"compId":380}]},{"type":"Sprite","props":{"y":1041,"x":1330,"scaleY":0.2,"scaleX":0.2,"name":"nanjun"},"compId":381,"child":[{"type":"Sprite","props":{"x":12,"texture":"image/国-宋.png","name":"hero"},"compId":382},{"type":"Sprite","props":{"y":147,"x":13,"texture":"image/国-宋.png","name":"soliders"},"compId":383},{"type":"Clip","props":{"y":324,"skin":"public/clip_num_blue.png","scaleY":5,"scaleX":5,"name":"moved","clipX":10},"compId":384},{"type":"Clip","props":{"y":150,"x":15,"skin":"public/clip_num_red.png","scaleY":5,"scaleX":5,"name":"moving","clipX":10},"compId":385}]},{"type":"Sprite","props":{"y":800.5,"x":1358,"scaleY":0.2,"scaleX":0.2,"name":"nanyang"},"compId":386,"child":[{"type":"Sprite","props":{"x":12,"texture":"image/国-宋.png","name":"hero"},"compId":387},{"type":"Sprite","props":{"y":147,"x":13,"texture":"image/国-宋.png","name":"soliders"},"compId":388},{"type":"Clip","props":{"y":324,"skin":"public/clip_num_blue.png","scaleY":5,"scaleX":5,"name":"moved","clipX":10},"compId":389},{"type":"Clip","props":{"y":150,"x":15,"skin":"public/clip_num_red.png","scaleY":5,"scaleX":5,"name":"moving","clipX":10},"compId":390}]},{"type":"Sprite","props":{"y":560,"x":1248.5,"scaleY":0.2,"scaleX":0.2,"name":"hedong"},"compId":391,"child":[{"type":"Sprite","props":{"x":12,"texture":"image/国-宋.png","name":"hero"},"compId":392},{"type":"Sprite","props":{"y":147,"x":13,"texture":"image/国-宋.png","name":"soliders"},"compId":393},{"type":"Clip","props":{"y":324,"skin":"public/clip_num_blue.png","scaleY":5,"scaleX":5,"name":"moved","clipX":10},"compId":394},{"type":"Clip","props":{"y":150,"x":15,"skin":"public/clip_num_red.png","scaleY":5,"scaleX":5,"name":"moving","clipX":10},"compId":395}]}]}]},{"type":"Sprite","props":{"y":-580,"x":14,"scaleY":0.6,"scaleX":0.6,"name":"diplomacy"},"compId":18,"child":[{"type":"Sprite","props":{"texture":"game/外交.png","scaleY":1,"scaleX":1,"name":"diplomacy"},"compId":6},{"type":"Sprite","props":{"y":120,"x":161,"texture":"image/状-回合.png","scaleY":0.13,"scaleX":0.13,"name":"round"},"compId":9},{"type":"Sprite","props":{"y":365,"x":395,"texture":"image/状-接见-a x6.png","scaleY":0.15,"scaleX":0.15,"name":"qi"},"compId":10},{"type":"Sprite","props":{"y":420,"x":445,"texture":"image/状-接见-b x6.png","scaleY":0.15,"scaleX":0.15,"name":"chu"},"compId":13},{"type":"Sprite","props":{"y":478,"x":272,"texture":"image/状-接见-a x6.png","scaleY":0.15,"scaleX":0.15,"name":"zhao"},"compId":14},{"type":"Sprite","props":{"y":709,"x":246,"texture":"image/状-接见-a x6.png","scaleY":0.15,"scaleX":0.15,"name":"wei"},"compId":15},{"type":"Sprite","props":{"y":762,"x":366,"texture":"image/状-接见-a x6.png","scaleY":0.15,"scaleX":0.15,"name":"han"},"compId":16},{"type":"Sprite","props":{"y":820,"x":300,"texture":"image/状-接见-a x6.png","scaleY":0.15,"scaleX":0.15,"name":"yan"},"compId":17}]},{"type":"Sprite","props":{"y":7,"x":1120,"name":"TianShi"},"compId":20,"child":[{"type":"Sprite","props":{"y":-0.5,"texture":"game/天时.png"},"compId":7},{"type":"Sprite","props":{"y":56.5,"x":23,"texture":"image/状-天时-a.png","scaleY":0.17,"scaleX":0.17,"name":"l"},"compId":12},{"type":"Sprite","props":{"y":56.5,"x":78,"texture":"image/状-天时-b.png","scaleY":0.17,"scaleX":0.17,"name":"h"},"compId":19}]},{"type":"Sprite","props":{"y":493,"x":242,"scaleY":0.4,"scaleX":0.4,"name":"cardBox"},"compId":29,"child":[{"type":"Sprite","props":{"texture":"card/合纵-名将出山.png","name":"item0"},"compId":22},{"type":"Sprite","props":{"x":338,"texture":"card/合纵-名将出山.png","name":"item1"},"compId":23},{"type":"Sprite","props":{"x":676,"texture":"card/合纵-名将出山.png","name":"item2"},"compId":24},{"type":"Sprite","props":{"x":1014,"texture":"card/合纵-名将出山.png","name":"item3"},"compId":25},{"type":"Sprite","props":{"x":1352,"texture":"card/合纵-名将出山.png","name":"item4"},"compId":26},{"type":"Sprite","props":{"x":1690,"texture":"card/合纵-名将出山.png","name":"item5"},"compId":27},{"type":"Sprite","props":{"x":2028,"texture":"card/合纵-名将出山.png","name":"item6"},"compId":28}]},{"type":"Sprite","props":{"y":616,"x":1190,"texture":"home/cardBag.png","name":"cardInHead"},"compId":31},{"type":"Sprite","props":{"y":392,"x":1178,"texture":"game/surrender.png","name":"surrender"},"compId":33},{"type":"Sprite","props":{"y":31,"x":31,"width":62,"texture":"game/dplm.png","pivotY":31,"pivotX":31,"name":"showDplm","height":62},"compId":34},{"type":"Sprite","props":{"y":378,"x":458,"name":"operation"},"compId":249,"child":[{"type":"Sprite","props":{"y":2,"texture":"game/mingchu.png","name":"mingchu"},"compId":246},{"type":"Sprite","props":{"y":22,"x":217,"texture":"game/pass.png","name":"pass"},"compId":247},{"type":"Sprite","props":{"x":108,"texture":"game/anchu.png","name":"anchu"},"compId":248}]},{"type":"Script","props":{"y":0,"x":0,"runtime":"script/GameControl.js"},"compId":32}],"loadList":["public/vscroll.png","public/hscroll.png","game/map.png","map/邯郸.png","map/韩.png","map/魏.png","map/齐郡.png","map/内史.png","map/上郡.png","map/东郡.png","map/中山.png","map/代郡.png","map/南郡.png","map/南阳.png","map/太原.png","map/宋.png","map/巴蜀.png","map/汉中.png","map/河东.png","map/泗水.png","map/陇西.png","map/琅琊.png","map/燕.png","map/淮夷.png","map/豫章.png","image/国-宋.png","public/clip_num_blue.png","public/clip_num_red.png","game/外交.png","image/状-回合.png","image/状-接见-a x6.png","image/状-接见-b x6.png","game/天时.png","image/状-天时-a.png","image/状-天时-b.png","card/合纵-名将出山.png","home/cardBag.png","game/surrender.png","game/dplm.png","game/mingchu.png","game/pass.png","game/anchu.png"],"loadList3D":[]}